Workbook
Name Accessories: Product_List!$A$5:$A$5
Name Electronic: Product_List!$A$1:$A$7
Name NativeTimeline_Date: #N/A
Name Office: Product_List!$A$7:$A$7
Name ProductCategories: OFFSET(Product_List!$B$1,1,0,COUNTA(Product_List!$B:$B)-1,1)
Name Slicer__Product_Category: #N/A
Name Slicer_Region: #N/A

Sheet Pivot 1_RevenueProfit
A3: Region | B3: Sum of Revenue | C3: Sum of Profit | D3: Sum of Profit Margin%
A4: East | B4: 104142 | C4: -8369.617 | D4: -0.080367354
A5: North | B5: 87013 | C5: -12968.72 | D5: -0.14904348
A6: South | B6: 124308 | C6: 2883.0782 | D6: 0.023193022
A7: West | B7: 125799 | C7: 6428.2592 | D7: 0.051099446
A8: Grand Total | B8: 441262 | C8: -12027 | D8: -0.027255916

Sheet Pivot2_CategoryProfit
A3: Product Category | B3: Sum of Profit
A4: Accessories | B4: 7673.8887
A5: Electronics | B5: -9588.2697
A6: Office | B6: -10112.619
A7: Grand Total | B7: -12027

Sheet Pivot_Classification
A3: Classificatin | B3: Count of CustomerID
A4: Low Value | B4: 21
A5: Regular | B5: 69
A6: Grand Total | B6: 90

Sheet Pivot4_
A3: Region | B3: Average of Delivery Days
A4: East | B4: 4.3809524
A5: North | B5: 4.5909091
A6: South | B6: 5.4347826
A7: West | B7: 5.0833333
A8: Grand Total | B8: 4.8888889

Sheet Dashboard
A1: Total Revenue | B1: Total Profit | C1: Top Customer | D1: On-Time Delivery%
A2: =SUM(Sales_All!K2:K97) -> 441262 | B2: =SUM(Sales_All!Q2:Q97) -> -12027 | C2: =INDEX(Sales_All!D2:D97,MATCH(MAX(Sales_All!R2:R97),Sales_All!R2:R97,0)) -> 1017 | D2: =COUNTIF(Sales_All!U2:U97,"<=5")/COUNTA(Sales_All!U2:U97) -> 0.58888889

Sheet Pivot_Top 5Products
A3: Products | B3: Sum of Revenue
A4: Headphones | B4: 92783 | D4: Products | E4: Sum of Revenue
A5: Laptop | B5: 100036 | D5: Headphones | E5: 92783
A6: Monitor | B6: 100690 | D6: Laptop | E6: 100036
A7: Printer | B7: 49991 | D7: Monitor | E7: 100690
A8: Tablet | B8: 60019 | D8: Printer | E8: 49991
A9: Grand Total | B9: 403519 | D9: Tablet | E9: 60019

Sheet Sales_All
A1: OrderID | B1: Date | C1: Region | D1: CustomerID | E1: Product | F1: Quantity | G1: UnitPrice | H1: Product Category | I1: Unit Cost | J1: Discount% | K1: Revenue | L1: Discounted Revenue | M1: Month Helper | N1: Monthly Overhead | O1: Orders This Month | P1: Allocated Overhead | Q1: Profit | R1: Customer Total Revenue | S1: Classificatin | T1: Index-Match | U1: Delivery Days | W1: Return Rate
A2: Q1-001 | B2: 45708.027 | C2: South | D2: 1018 | E2: Tablet | F2: 1 | G2: 730 | H2: =_xlfn.XLOOKUP(TRIM(E2),Product_List!A:A,Product_List!B:B) -> Electronics | I2: =_xlfn.XLOOKUP(TRIM(E2),Product_List!A:A,Product_List!D:D) -> 492 | J2: =_xlfn.XLOOKUP(TRIM(E2),Product_List!A:A,Product_List!E:E) -> 0.14 | K2: =F2*G2 -> 730 | L2: =K2*(1-J2) -> 627.8 | M2: =EOMONTH(B2,0) -> 45716 | N2: =_xlfn.XLOOKUP(M2,Finance_Data!A:A,Finance_Data!B:B) -> 43320 | O2: =COUNTIF($M$2:$M$97,M2) -> 10 | P2: =N2/O2 -> 4332 | Q2: =K2-(F2*I2)-P2 -> -4094 | R2: =SUMIF($D$2:$D$97,D2,$K$2:$K$97) -> 31997 | S2: {=_xlfn.IFS(R2>50000,"VIP",R2>=20000,"Regular",TRUE,"Low Value")} -> Regular | T2: =INDEX(Product_List!B:B,MATCH(E3,Product_List!A:A,0)) -> Accessories | U2: =_xlfn.XLOOKUP(A2,Operations_Data!A:A,Operations_Data!B:B) -> 5 | W2: =_xlfn.XLOOKUP(A2,Operations_Data!A:A,Operations_Data!C:C) -> 0.01
A3: Q1-002 | B3: 45712.237 | C3: South | D3: 1004 | E3: Headphones | F3: 3 | G3: 378 | H3: =_xlfn.XLOOKUP(TRIM(E3),Product_List!A:A,Product_List!B:B) -> Accessories | I3: =_xlfn.XLOOKUP(TRIM(E3),Product_List!A:A,Product_List!D:D) -> 323 | J3: =_xlfn.XLOOKUP(TRIM(E3),Product_List!A:A,Product_List!E:E) -> 0.1 | K3: =F3*G3 -> 1134 | L3: =K3*(1-J3) -> 1020.6 | M3: =EOMONTH(B3,0) -> 45716 | N3: =_xlfn.XLOOKUP(M3,Finance_Data!A:A,Finance_Data!B:B) -> 43320 | O3: =COUNTIF($M$2:$M$97,M3) -> 10 | P3: =N3/O3 -> 4332 | Q3: =K3-(F3*I3)-P3 -> -4167 | R3: =SUMIF($D$2:$D$97,D3,$K$2:$K$97) -> 8004 | S3: {=_xlfn.IFS(R3>50000,"VIP",R3>=20000,"Regular",TRUE,"Low Value")} -> Low Value | T3: =INDEX(Product_List!B:B,MATCH(E4,Product_List!A:A,0)) -> Electronics | U3: =_xlfn.XLOOKUP(A3,Operations_Data!A:A,Operations_Data!B:B) -> 2 | W3: =_xlfn.XLOOKUP(A3,Operations_Data!A:A,Operations_Data!C:C) -> 0.03
A4: Q1-003 | B4: 45736.268 | C4: West | D4: 1005 | E4: Monitor | F4: 1 | G4: 585 | H4: =_xlfn.XLOOKUP(TRIM(E4),Product_List!A:A,Product_List!B:B) -> Electronics | I4: =_xlfn.XLOOKUP(TRIM(E4),Product_List!A:A,Product_List!D:D) -> 463 | J4: =_xlfn.XLOOKUP(TRIM(E4),Product_List!A:A,Product_List!E:E) -> 0.23 | K4: =F4*G4 -> 585 | L4: =K4*(1-J4) -> 450.45 | M4: =EOMONTH(B4,0) -> 45747 | N4: =_xlfn.XLOOKUP(M4,Finance_Data!A:A,Finance_Data!B:B) -> 34147 | O4: =COUNTIF($M$2:$M$97,M4) -> 10 | P4: =N4/O4 -> 3414.7 | Q4: =K4-(F4*I4)-P4 -> -3292.7 | R4: =SUMIF($D$2:$D$97,D4,$K$2:$K$97) -> 24821 | S4: {=_xlfn.IFS(R4>50000,"VIP",R4>=20000,"Regular",TRUE,"Low Value")} -> Regular | T4: =INDEX(Product_List!B:B,MATCH(E5,Product_List!A:A,0)) -> Electronics | U4: =_xlfn.XLOOKUP(A4,Operations_Data!A:A,Operations_Data!B:B) -> 6 | W4: =_xlfn.XLOOKUP(A4,Operations_Data!A:A,Operations_Data!C:C) -> 0.05
A5: Q1-004 | B5: 45703.571 | C5: East | D5: 1018 | E5: Smartphone | F5: 8 | G5: 726 | H5: =_xlfn.XLOOKUP(TRIM(E5),Product_List!A:A,Product_List!B:B) -> Electronics | I5: =_xlfn.XLOOKUP(TRIM(E5),Product_List!A:A,Product_List!D:D) -> 97 | J5: =_xlfn.XLOOKUP(TRIM(E5),Product_List!A:A,Product_List!E:E) -> 0.08 | K5: =F5*G5 -> 5808 | L5: =K5*(1-J5) -> 5343.36 | M5: =EOMONTH(B5,0) -> 45716 | N5: =_xlfn.XLOOKUP(M5,Finance_Data!A:A,Finance_Data!B:B) -> 43320 | O5: =COUNTIF($M$2:$M$97,M5) -> 10 | P5: =N5/O5 -> 4332 | Q5: =K5-(F5*I5)-P5 -> 700 | R5: =SUMIF($D$2:$D$97,D5,$K$2:$K$97) -> 31997 | S5: {=_xlfn.IFS(R5>50000,"VIP",R5>=20000,"Regular",TRUE,"Low Value")} -> Regular | T5: =INDEX(Product_List!B:B,MATCH(E6,Product_List!A:A,0)) -> Electronics | U5: =_xlfn.XLOOKUP(A5,Operations_Data!A:A,Operations_Data!B:B) -> 4 | W5: =_xlfn.XLOOKUP(A5,Operations_Data!A:A,Operations_Data!C:C) -> 0.07
A6: Q1-005 | B6: 45663.686 | C6: North | D6: 1012 | E6: Laptop | F6: 2 | G6: 709 | H6: =_xlfn.XLOOKUP(TRIM(E6),Product_List!A:A,Product_List!B:B) -> Electronics | I6: =_xlfn.XLOOKUP(TRIM(E6),Product_List!A:A,Product_List!D:D) -> 469 | J6: =_xlfn.XLOOKUP(TRIM(E6),Product_List!A:A,Product_List!E:E) -> 0.22 | K6: =F6*G6 -> 1418 | L6: =K6*(1-J6) -> 1106.04 | M6: =EOMONTH(B6,0) -> 45688 | N6: =_xlfn.XLOOKUP(M6,Finance_Data!A:A,Finance_Data!B:B) -> 25640 | O6: =COUNTIF($M$2:$M$97,M6) -> 10 | P6: =N6/O6 -> 2564 | Q6: =K6-(F6*I6)-P6 -> -2084 | R6: =SUMIF($D$2:$D$97,D6,$K$2:$K$97) -> 8379 | S6: {=_xlfn.IFS(R6>50000,"VIP",R6>=20000,"Regular",TRUE,"Low Value")} -> Low Value | T6: =INDEX(Product_List!B:B,MATCH(E7,Product_List!A:A,0)) -> Electronics | U6: =_xlfn.XLOOKUP(A6,Operations_Data!A:A,Operations_Data!B:B) -> 5 | W6: =_xlfn.XLOOKUP(A6,Operations_Data!A:A,Operations_Data!C:C) -> 0.03
A7: Q1-006 | B7: 45716.227 | C7: East | D7: 1013 | E7: Laptop | F7: 8 | G7: 1817 | H7: =_xlfn.XLOOKUP(TRIM(E7),Product_List!A:A,Product_List!B:B) -> Electronics | I7: =_xlfn.XLOOKUP(TRIM(E7),Product_List!A:A,Product_List!D:D) -> 469 | J7: =_xlfn.XLOOKUP(TRIM(E7),Product_List!A:A,Product_List!E:E) -> 0.22 | K7: =F7*G7 -> 14536 | L7: =K7*(1-J7) -> 11338.08 | M7: =EOMONTH(B7,0) -> 45716 | N7: =_xlfn.XLOOKUP(M7,Finance_Data!A:A,Finance_Data!B:B) -> 43320 | O7: =COUNTIF($M$2:$M$97,M7) -> 10 | P7: =N7/O7 -> 4332 | Q7: =K7-(F7*I7)-P7 -> 6452 | R7: =SUMIF($D$2:$D$97,D7,$K$2:$K$97) -> 17364 | S7: {=_xlfn.IFS(R7>50000,"VIP",R7>=20000,"Regular",TRUE,"Low Value")} -> Low Value | T7: =INDEX(Product_List!B:B,MATCH(E8,Product_List!A:A,0)) -> Electronics | U7: =_xlfn.XLOOKUP(A7,Operations_Data!A:A,Operations_Data!B:B) -> 5 | W7: =_xlfn.XLOOKUP(A7,Operations_Data!A:A,Operations_Data!C:C) -> 0.06
A8: Q1-007 | B8: 45735.116 | C8: South | D8: 1017 | E8: Tablet | F8: 9 | G8: 1976 | H8: =_xlfn.XLOOKUP(TRIM(E8),Product_List!A:A,Product_List!B:B) -> Electronics | I8: =_xlfn.XLOOKUP(TRIM(E8),Product_List!A:A,Product_List!D:D) -> 492 | J8: =_xlfn.XLOOKUP(TRIM(E8),Product_List!A:A,Product_List!E:E) -> 0.14 | K8: =F8*G8 -> 17784 | L8: =K8*(1-J8) -> 15294.24 | M8: =EOMONTH(B8,0) -> 45747 | N8: =_xlfn.XLOOKUP(M8,Finance_Data!A:A,Finance_Data!B:B) -> 34147 | O8: =COUNTIF($M$2:$M$97,M8) -> 10 | P8: =N8/O8 -> 3414.7 | Q8: =K8-(F8*I8)-P8 -> 9941.3 | R8: =SUMIF($D$2:$D$97,D8,$K$2:$K$97) -> 38912 | S8: {=_xlfn.IFS(R8>50000,"VIP",R8>=20000,"Regular",TRUE,"Low Value")} -> Regular | T8: =INDEX(Product_List!B:B,MATCH(E9,Product_List!A:A,0)) -> Electronics | U8: =_xlfn.XLOOKUP(A8,Operations_Data!A:A,Operations_Data!B:B) -> 4 | W8: =_xlfn.XLOOKUP(A8,Operations_Data!A:A,Operations_Data!C:C) -> 0.02
A9: Q1-008 | B9: 45707.394 | C9: South | D9: 1014 | E9: Tablet | F9: 5 | G9: 1134 | H9: =_xlfn.XLOOKUP(TRIM(E9),Product_List!A:A,Product_List!B:B) -> Electronics | I9: =_xlfn.XLOOKUP(TRIM(E9),Product_List!A:A,Product_List!D:D) -> 492 | J9: =_xlfn.XLOOKUP(TRIM(E9),Product_List!A:A,Product_List!E:E) -> 0.14 | K9: =F9*G9 -> 5670 | L9: =K9*(1-J9) -> 4876.2 | M9: =EOMONTH(B9,0) -> 45716 | N9: =_xlfn.XLOOKUP(M9,Finance_Data!A:A,Finance_Data!B:B) -> 43320 | O9: =COUNTIF($M$2:$M$97,M9) -> 10 | P9: =N9/O9 -> 4332 | Q9: =K9-(F9*I9)-P9 -> -1122 | R9: =SUMIF($D$2:$D$97,D9,$K$2:$K$97) -> 31571 | S9: {=_xlfn.IFS(R9>50000,"VIP",R9>=20000,"Regular",TRUE,"Low Value")} -> Regular | T9: =INDEX(Product_List!B:B,MATCH(E10,Product_List!A:A,0)) -> Office | U9: =_xlfn.XLOOKUP(A9,Operations_Data!A:A,Operations_Data!B:B) -> 8 | W9: =_xlfn.XLOOKUP(A9,Operations_Data!A:A,Operations_Data!C:C) -> 0.07
A10: Q1-009 | B10: 45671.497 | C10: South | D10: 1020 | E10: Printer | F10: 1 | G10: 1220 | H10: =_xlfn.XLOOKUP(TRIM(E10),Product_List!A:A,Product_List!B:B) -> Office | I10: =_xlfn.XLOOKUP(TRIM(E10),Product_List!A:A,Product_List!D:D) -> 136 | J10: =_xlfn.XLOOKUP(TRIM(E10),Product_List!A:A,Product_List!E:E) -> 0.1 | K10: =F10*G10 -> 1220 | L10: =K10*(1-J10) -> 1098 | M10: =EOMONTH(B10,0) -> 45688 | N10: =_xlfn.XLOOKUP(M10,Finance_Data!A:A,Finance_Data!B:B) -> 25640 | O10: =COUNTIF($M$2:$M$97,M10) -> 10 | P10: =N10/O10 -> 2564 | Q10: =K10-(F10*I10)-P10 -> -1480 | R10: =SUMIF($D$2:$D$97,D10,$K$2:$K$97) -> 21494 | S10: {=_xlfn.IFS(R10>50000,"VIP",R10>=20000,"Regular",TRUE,"Low Value")} -> Regular | T10: =INDEX(Product_List!B:B,MATCH(E11,Product_List!A:A,0)) -> Accessories | U10: =_xlfn.XLOOKUP(A10,Operations_Data!A:A,Operations_Data!B:B) -> 2 | W10: =_xlfn.XLOOKUP(A10,Operations_Data!A:A,Operations_Data!C:C) -> 0.08
A11: Q1-010 | B11: 45743.202 | C11: West | D11: 1010 | E11: Headphones | F11: 2 | G11: 283 | H11: =_xlfn.XLOOKUP(TRIM(E11),Product_List!A:A,Product_List!B:B) -> Accessories | I11: =_xlfn.XLOOKUP(TRIM(E11),Product_List!A:A,Product_List!D:D) -> 323 | J11: =_xlfn.XLOOKUP(TRIM(E11),Product_List!A:A,Product_List!E:E) -> 0.1 | K11: =F11*G11 -> 566 | L11: =K11*(1-J11) -> 509.4 | M11: =EOMONTH(B11,0) -> 45747 | N11: =_xlfn.XLOOKUP(M11,Finance_Data!A:A,Finance_Data!B:B) -> 34147 | O11: =COUNTIF($M$2:$M$97,M11) -> 10 | P11: =N11/O11 -> 3414.7 | Q11: =K11-(F11*I11)-P11 -> -3494.7 | R11: =SUMIF($D$2:$D$97,D11,$K$2:$K$97) -> 23446 | S11: {=_xlfn.IFS(R11>50000,"VIP",R11>=20000,"Regular",TRUE,"Low Value")} -> Regular | T11: =INDEX(Product_List!B:B,MATCH(E12,Product_List!A:A,0)) -> Electronics | U11: =_xlfn.XLOOKUP(A11,Operations_Data!A:A,Operations_Data!B:B) -> 2 | W11: =_xlfn.XLOOKUP(A11,Operations_Data!A:A,Operations_Data!C:C) -> 0.08
A12: Q1-011 | B12: 45684.929 | C12: West | D12: 1019 | E12: Laptop | F12: 9 | G12: 417 | H12: =_xlfn.XLOOKUP(TRIM(E12),Product_List!A:A,Product_List!B:B) -> Electronics | I12: =_xlfn.XLOOKUP(TRIM(E12),Product_List!A:A,Product_List!D:D) -> 469 | J12: =_xlfn.XLOOKUP(TRIM(E12),Product_List!A:A,Product_List!E:E) -> 0.22 | K12: =F12*G12 -> 3753 | L12: =K12*(1-J12) -> 2927.34 | M12: =EOMONTH(B12,0) -> 45688 | N12: =_xlfn.XLOOKUP(M12,Finance_Data!A:A,Finance_Data!B:B) -> 25640 | O12: =COUNTIF($M$2:$M$97,M12) -> 10 | P12: =N12/O12 -> 2564 | Q12: =K12-(F12*I12)-P12 -> -3032 | R12: =SUMIF($D$2:$D$97,D12,$K$2:$K$97) -> 20633 | S12: {=_xlfn.IFS(R12>50000,"VIP",R12>=20000,"Regular",TRUE,"Low Value")} -> Regular | T12: =INDEX(Product_List!B:B,MATCH(E13,Product_List!A:A,0)) -> Electronics | U12: =_xlfn.XLOOKUP(A12,Operations_Data!A:A,Operations_Data!B:B) -> 8 | W12: =_xlfn.XLOOKUP(A12,Operations_Data!A:A,Operations_Data!C:C) -> 0.06
A13: Q1-012 | B13: 45662.79 | C13: South | D13: 1016 | E13: Laptop | F13: 3 | G13: 1692 | H13: =_xlfn.XLOOKUP(TRIM(E13),Product_List!A:A,Product_List!B:B) -> Electronics | I13: =_xlfn.XLOOKUP(TRIM(E13),Product_List!A:A,Product_List!D:D) -> 469 | J13: =_xlfn.XLOOKUP(TRIM(E13),Product_List!A:A,Product_List!E:E) -> 0.22 | K13: =F13*G13 -> 5076 | L13: =K13*(1-J13) -> 3959.28 | M13: =EOMONTH(B13,0) -> 45688 | N13: =_xlfn.XLOOKUP(M13,Finance_Data!A:A,Finance_Data!B:B) -> 25640 | O13: =COUNTIF($M$2:$M$97,M13) -> 10 | P13: =N13/O13 -> 2564 | Q13: =K13-(F13*I13)-P13 -> 1105 | R13: =SUMIF($D$2:$D$97,D13,$K$2:$K$97) -> 22009 | S13: {=_xlfn.IFS(R13>50000,"VIP",R13>=20000,"Regular",TRUE,"Low Value")} -> Regular | T13: =INDEX(Product_List!B:B,MATCH(E14,Product_List!A:A,0)) -> Office | U13: =_xlfn.XLOOKUP(A13,Operations_Data!A:A,Operations_Data!B:B) -> 8 | W13: =_xlfn.XLOOKUP(A13,Operations_Data!A:A,Operations_Data!C:C) -> 0.03
... A90: Q3-029 | B90: 45889.658 | C90: North | D90: 1019 | E90: Monitor | F90: 5 | G90: 698 | H90: =_xlfn.XLOOKUP(TRIM(E90),Product_List!A:A,Product_List!B:B) -> Electronics | I90: =_xlfn.XLOOKUP(TRIM(E90),Product_List!A:A,Product_List!D:D) -> 463 | J90: =_xlfn.XLOOKUP(TRIM(E90),Product_List!A:A,Product_List!E:E) -> 0.23 | K90: =F90*G90 -> 3490 | L90: =K90*(1-J90) -> 2687.3 | M90: =EOMONTH(B90,0) -> 45900 | N90: =_xlfn.XLOOKUP(M90,Finance_Data!A:A,Finance_Data!B:B) -> 36734 | O90: =COUNTIF($M$2:$M$97,M90) -> 11 | P90: =N90/O90 -> 3339.4545 | Q90: =K90-(F90*I90)-P90 -> -2164.4545 | R90: =SUMIF($D$2:$D$97,D90,$K$2:$K$97) -> 20633 | S90: {=_xlfn.IFS(R90>50000,"VIP",R90>=20000,"Regular",TRUE,"Low Value")} -> Regular | T90: =INDEX(Product_List!B:B,MATCH(E91,Product_List!A:A,0)) -> Electronics | U90: =_xlfn.XLOOKUP(A90,Operations_Data!A:A,Operations_Data!B:B) -> 4 | W90: =_xlfn.XLOOKUP(A90,Operations_Data!A:A,Operations_Data!C:C) -> 0.07
A91: Q3-030 | B91: 45898.259 | C91: West | D91: 1003 | E91: Monitor | F91: 3 | G91: 651 | H91: =_xlfn.XLOOKUP(TRIM(E91),Product_List!A:A,Product_List!B:B) -> Electronics | I91: =_xlfn.XLOOKUP(TRIM(E91),Product_List!A:A,Product_List!D:D) -> 463 | J91: =_xlfn.XLOOKUP(TRIM(E91),Product_List!A:A,Product_List!E:E) -> 0.23 | K91: =F91*G91 -> 1953 | L91: =K91*(1-J91) -> 1503.81 | M91: =EOMONTH(B91,0) -> 45900 | N91: =_xlfn.XLOOKUP(M91,Finance_Data!A:A,Finance_Data!B:B) -> 36734 | O91: =COUNTIF($M$2:$M$97,M91) -> 11 | P91: =N91/O91 -> 3339.4545 | Q91: =K91-(F91*I91)-P91 -> -2775.4545 | R91: =SUMIF($D$2:$D$97,D91,$K$2:$K$97) -> 31251 | S91: {=_xlfn.IFS(R91>50000,"VIP",R91>=20000,"Regular",TRUE,"Low Value")} -> Regular | T91: =INDEX(Product_List!B:B,MATCH(E2,Product_List!A:A,0)) -> Electronics | U91: =_xlfn.XLOOKUP(A91,Operations_Data!A:A,Operations_Data!B:B) -> 5 | W91: =_xlfn.XLOOKUP(A91,Operations_Data!A:A,Operations_Data!C:C) -> 0.09

Sheet Operations_Data
A1: OrderID | B1: DeliveryDays | C1: ReturnRate
A2: Q1-001 | B2: 5 | C2: 0.01
A3: Q1-002 | B3: 2 | C3: 0.03
A4: Q1-003 | B4: 6 | C4: 0.05
A5: Q1-004 | B5: 4 | C5: 0.07
A6: Q1-005 | B6: 5 | C6: 0.03
A7: Q1-006 | B7: 5 | C7: 0.06
A8: Q1-007 | B8: 4 | C8: 0.02
A9: Q1-008 | B9: 8 | C9: 0.07
A10: Q1-009 | B10: 2 | C10: 0.08
A11: Q1-010 | B11: 2 | C11: 0.08
A12: Q1-011 | B12: 8 | C12: 0.06
A13: Q1-012 | B13: 8 | C13: 0.03
... A91: Q3-030 | B91: 5 | C91: 0.09

Sheet Region_Summary
A1: Unique list of Regions | B1: Count orders per Region | C1: Average
A2: {=_xlfn.UNIQUE(Sales_All!C2:C97)} -> South | B2: =COUNTIF(Sales_All!$C$2:$C$97,A2) -> 23 | C2: =AVERAGEIF(Sales_All!$C$2:$C$97,A2,Sales_All!$U$2:$U$97) -> 5.4347826
A3: West | B3: =COUNTIF(Sales_All!$C$2:$C$97,A3) -> 24 | C3: =AVERAGEIF(Sales_All!$C$2:$C$97,A3,Sales_All!$U$2:$U$97) -> 5.0833333
A4: East | B4: =COUNTIF(Sales_All!$C$2:$C$97,A4) -> 21 | C4: =AVERAGEIF(Sales_All!$C$2:$C$97,A4,Sales_All!$U$2:$U$97) -> 4.3809524
A5: North | B5: =COUNTIF(Sales_All!$C$2:$C$97,A5) -> 22 | C5: =AVERAGEIF(Sales_All!$C$2:$C$97,A5,Sales_All!$U$2:$U$97) -> 4.5909091
A6: 0
A7: East | B7: Accessories

Sheet Finance_Data
A2: Month | B2: Overheads | C2: Salaries | D2: OtherExpenses | E2: NetProfit
A3: 45688 | B3: 25640 | C3: 60082 | D3: 21492 | E3: =C3-B3 -> 34442
A4: 45716 | B4: 43320 | C4: 70533 | D4: 27724 | E4: =C4-B4 -> 27213
A5: 45747 | B5: 34147 | C5: 63890 | D5: 17738 | E5: =C5-B5 -> 29743
A6: 45777 | B6: 44423 | C6: 90674 | D6: 21152 | E6: =C6-B6 -> 46251
A7: 45808 | B7: 32119 | C7: 55646 | D7: 19723 | E7: =C7-B7 -> 23527
A8: 45838 | B8: 20079 | C8: 99954 | D8: 15769 | E8: =C8-B8 -> 79875
A9: 45869 | B9: 36304 | C9: 63297 | D9: 25453 | E9: =C9-B9 -> 26993
A10: 45900 | B10: 36734 | C10: 93760 | D10: 16230 | E10: =C10-B10 -> 57026
A11: 45930 | B11: 34260 | C11: 70760 | D11: 28818 | E11: =C11-B11 -> 36500

Sheet Product_List
A1: Product | B1: Category | C1: UnitPrice | D1: UnitCost | E1: Discount
A2: Laptop | B2: Electronics | C2: 1299 | D2: 469 | E2: 0.22
A3: Tablet | B3: Electronics | C3: 1613 | D3: 492 | E3: 0.14
A4: Smartphone | B4: Electronics | C4: 1402 | D4: 97 | E4: 0.08
A5: Headphones | B5: Accessories | C5: 106 | D5: 323 | E5: 0.1
A6: Monitor | B6: Electronics | C6: 396 | D6: 463 | E6: 0.23
A7: Printer | B7: Office | C7: 1635 | D7: 136 | E7: 0.1

Sheet Sheet1

Sheet Customer_List
A1: CustomerID | B1: FirstName | C1: LastName | D1: Clean FirstName | E1: Clean LastName | F1: Product a customer bought | G1: Email | H1: Email Domain | I1: Region
A2: 1001 | B2: Naledi | C2: Pillay | D2: =PROPER(B2) -> Naledi | E2: =PROPER(C2) -> Pillay | F2: {=_xlfn.TEXTJOIN(", ",TRUE,IF(Sales_All!$D$2:$D$97=A2,Sales_All!$E$2:$E$97,""))} -> Printer, Monitor, Smartphone, Headphones, Monitor, Monitor, Laptop, Laptop | G2: naledi.pillay@example.com | H2: =RIGHT(G2,LEN(G2)-FIND("@",G2)) -> example.com | I2: East
A3: 1002 | B3: Michael | C3: van Wyk | D3: =PROPER(B3) -> Michael | E3: =PROPER(C3) -> Van Wyk | G3: michael.van wyk@example.com | H3: =RIGHT(G3,LEN(G3)-FIND("@",G3)) -> example.com | I3: East
A4: 1003 | B4: Naledi | C4: Botha | D4: =PROPER(B4) -> Naledi | E4: =PROPER(C4) -> Botha | F4: {=_xlfn.TEXTJOIN(", ",TRUE,IF(Sales_All!$D$2:$D$97=A4,Sales_All!$E$2:$E$97,""))} -> Printer, Monitor, Headphones, Monitor | G4: naledi.botha@example.com | H4: =RIGHT(G4,LEN(G4)-FIND("@",G4)) -> example.com | I4: East
A5: 1004 | B5: Naledi | C5: Botha | D5: =PROPER(B5) -> Naledi | E5: =PROPER(C5) -> Botha | G5: naledi.botha@example.com | H5: =RIGHT(G5,LEN(G5)-FIND("@",G5)) -> example.com | I5: North
A6: 1005 | B6: Michael | C6: Johnson | D6: =PROPER(B6) -> Michael | E6: =PROPER(C6) -> Johnson | F6: {=_xlfn.TEXTJOIN(", ",TRUE,IF(Sales_All!$D$2:$D$97=A6,Sales_All!$E$2:$E$97,""))} -> Monitor, Printer, Printer, Printer, Tablet | G6: michael.johnson@example.com | H6: =RIGHT(G6,LEN(G6)-FIND("@",G6)) -> example.com | I6: North
A7: 1006 | B7: Emily | C7: Johnson | D7: =PROPER(B7) -> Emily | E7: =PROPER(C7) -> Johnson | G7: emily.johnson@example.com | H7: =RIGHT(G7,LEN(G7)-FIND("@",G7)) -> example.com | I7: South
A8: 1007 | B8: Michael | C8: Nguyen | D8: =PROPER(B8) -> Michael | E8: =PROPER(C8) -> Nguyen | F8: {=_xlfn.TEXTJOIN(", ",TRUE,IF(Sales_All!$D$2:$D$97=A8,Sales_All!$E$2:$E$97,""))} -> Monitor, Laptop, Smartphone, Monitor | G8: michael.nguyen@example.com | H8: =RIGHT(G8,LEN(G8)-FIND("@",G8)) -> example.com | I8: West
A9: 1008 | B9: Sipho | C9: Johnson | D9: =PROPER(B9) -> Sipho | E9: =PROPER(C9) -> Johnson | G9: sipho.johnson@example.com | H9: =RIGHT(G9,LEN(G9)-FIND("@",G9)) -> example.com | I9: East
A10: 1009 | B10: Sarah | C10: Nguyen | D10: =PROPER(B10) -> Sarah | E10: =PROPER(C10) -> Nguyen | F10: {=_xlfn.TEXTJOIN(", ",TRUE,IF(Sales_All!$D$2:$D$97=A10,Sales_All!$E$2:$E$97,""))} -> Monitor, Headphones, Smartphone, Laptop, Printer, Smartphone | G10: sarah.nguyen@example.com | H10: =RIGHT(G10,LEN(G10)-FIND("@",G10)) -> example.com | I10: North
A11: 1010 | B11: John | C11: Brown | D11: =PROPER(B11) -> John | E11: =PROPER(C11) -> Brown | G11: john.brown@example.com | H11: =RIGHT(G11,LEN(G11)-FIND("@",G11)) -> example.com | I11: East
A12: 1011 | B12: John | C12: Smith | D12: =PROPER(B12) -> John | E12: =PROPER(C12) -> Smith | F12: {=_xlfn.TEXTJOIN(", ",TRUE,IF(Sales_All!$D$2:$D$97=A12,Sales_All!$E$2:$E$97,""))} -> Printer, Headphones, Tablet | G12: john.smith@example.com | H12: =RIGHT(G12,LEN(G12)-FIND("@",G12)) -> example.com | I12: South
A13: 1012 | B13: Naledi | C13: van Wyk | D13: =PROPER(B13) -> Naledi | E13: =PROPER(C13) -> Van Wyk | G13: naledi.van wyk@example.com | H13: =RIGHT(G13,LEN(G13)-FIND("@",G13)) -> example.com | I13: East
A14: 1013 | B14: Sipho | C14: van Wyk | D14: =PROPER(B14) -> Sipho | E14: =PROPER(C14) -> Van Wyk | F14: {=_xlfn.TEXTJOIN(", ",TRUE,IF(Sales_All!$D$2:$D$97=A14,Sales_All!$E$2:$E$97,""))} -> Laptop, Printer | G14: sipho.van wyk@example.com | H14: =RIGHT(G14,LEN(G14)-FIND("@",G14)) -> example.com | I14: South
A15: 1014 | B15: John | C15: Mlambo | D15: =PROPER(B15) -> John | E15: =PROPER(C15) -> Mlambo | G15: john.mlambo@example.com | H15: =RIGHT(G15,LEN(G15)-FIND("@",G15)) -> example.com | I15: East
A16: 1015 | B16: John | C16: Smith | D16: =PROPER(B16) -> John | E16: =PROPER(C16) -> Smith | F16: {=_xlfn.TEXTJOIN(", ",TRUE,IF(Sales_All!$D$2:$D$97=A16,Sales_All!$E$2:$E$97,""))} -> Smartphone, Smartphone | G16: john.smith@example.com | H16: =RIGHT(G16,LEN(G16)-FIND("@",G16)) -> example.com | I16: South
A17: 1016 | B17: Sipho | C17: Nguyen | D17: =PROPER(B17) -> Sipho | E17: =PROPER(C17) -> Nguyen | G17: sipho.nguyen@example.com | H17: =RIGHT(G17,LEN(G17)-FIND("@",G17)) -> example.com | I17: West
A18: 1017 | B18: Sipho | C18: Smith | D18: =PROPER(B18) -> Sipho | E18: =PROPER(C18) -> Smith | F18: {=_xlfn.TEXTJOIN(", ",TRUE,IF(Sales_All!$D$2:$D$97=A18,Sales_All!$E$2:$E$97,""))} -> Tablet, Laptop, Printer, Laptop, Smartphone | G18: sipho.smith@example.com | H18: =RIGHT(G18,LEN(G18)-FIND("@",G18)) -> example.com | I18: North
A19: 1018 | B19: Michael | C19: Mlambo | D19: =PROPER(B19) -> Michael | E19: =PROPER(C19) -> Mlambo | G19: michael.mlambo@example.com | H19: =RIGHT(G19,LEN(G19)-FIND("@",G19)) -> example.com | I19: South
A20: 1019 | B20: Naledi | C20: Nguyen | D20: =PROPER(B20) -> Naledi | E20: =PROPER(C20) -> Nguyen | F20: {=_xlfn.TEXTJOIN(", ",TRUE,IF(Sales_All!$D$2:$D$97=A20,Sales_All!$E$2:$E$97,""))} -> Laptop, Laptop, Headphones, Laptop, Tablet, Tablet, Monitor | G20: naledi.nguyen@example.com | H20: =RIGHT(G20,LEN(G20)-FIND("@",G20)) -> example.com | I20: North
A21: 1020 | B21: David | C21: van Wyk | D21: =PROPER(B21) -> David | E21: =PROPER(C21) -> Van Wyk | G21: david.van wyk@example.com | H21: =RIGHT(G21,LEN(G21)-FIND("@",G21)) -> example.com | I21: West
A22: 1021 | B22: Thabo | C22: Botha | D22: =PROPER(B22) -> Thabo | E22: =PROPER(C22) -> Botha | F22: {=_xlfn.TEXTJOIN(", ",TRUE,IF(Sales_All!$D$2:$D$97=A22,Sales_All!$E$2:$E$97,""))} | G22: thabo.botha@example.com | H22: =RIGHT(G22,LEN(G22)-FIND("@",G22)) -> example.com | I22: South
A23: 1022 | B23: Sipho | C23: van Wyk | D23: =PROPER(B23) -> Sipho | E23: =PROPER(C23) -> Van Wyk | G23: sipho.van wyk@example.com | H23: =RIGHT(G23,LEN(G23)-FIND("@",G23)) -> example.com | I23: West
A24: 1023 | B24: Lerato | C24: Naidoo | D24: =PROPER(B24) -> Lerato | E24: =PROPER(C24) -> Naidoo | F24: {=_xlfn.TEXTJOIN(", ",TRUE,IF(Sales_All!$D$2:$D$97=A24,Sales_All!$E$2:$E$97,""))} | G24: lerato.naidoo@example.com | H24: =RIGHT(G24,LEN(G24)-FIND("@",G24)) -> example.com | I24: West
A25: 1024 | B25: Aisha | C25: Brown | D25: =PROPER(B25) -> Aisha | E25: =PROPER(C25) -> Brown | G25: aisha.brown@example.com | H25: =RIGHT(G25,LEN(G25)-FIND("@",G25)) -> example.com | I25: East
A26: 1025 | B26: Lerato | C26: van Wyk | D26: =PROPER(B26) -> Lerato | E26: =PROPER(C26) -> Van Wyk | F26: {=_xlfn.TEXTJOIN(", ",TRUE,IF(Sales_All!$D$2:$D$97=A26,Sales_All!$E$2:$E$97,""))} | G26: lerato.van wyk@example.com | H26: =RIGHT(G26,LEN(G26)-FIND("@",G26)) -> example.com | I26: East
A27: 1015 | B27: John | C27: Smith | D27: =PROPER(B27) -> John | E27: =PROPER(C27) -> Smith | G27: john.smith@example.com | H27: =RIGHT(G27,LEN(G27)-FIND("@",G27)) -> example.com | I27: South
A28: 1014 | B28: John | C28: Mlambo | D28: =PROPER(B28) -> John | E28: =PROPER(C28) -> Mlambo | F28: {=_xlfn.TEXTJOIN(", ",TRUE,IF(Sales_All!$D$2:$D$97=A28,Sales_All!$E$2:$E$97,""))} -> Tablet, Monitor, Headphones | G28: john.mlambo@example.com | H28: =RIGHT(G28,LEN(G28)-FIND("@",G28)) -> example.com | I28: East
A29: 1018 | B29: Michael | C29: Mlambo | D29: =PROPER(B29) -> Michael | E29: =PROPER(C29) -> Mlambo | G29: michael.mlambo@example.com | H29: =RIGHT(G29,LEN(G29)-FIND("@",G29)) -> example.com | I29: South

Sheet Summary
